Workbook

Sheet Dashboard
A1: Dashboard
A3: Revenue | B3: =(SUMIFS(Inventory!$Q$2:$Q$501,Inventory!$L$2:$L$501,"Sold")+SUMIFS(Inventory!$Q$2:$Q$501,Inventory!$L$2:$L$501,"Shipped")) -> 32
A4: Fees | B4: =(SUMIFS(Inventory!$R$2:$R$501,Inventory!$L$2:$L$501,"Sold")+SUMIFS(Inventory!$R$2:$R$501,Inventory!$L$2:$L$501,"Shipped")) -> 1.51
A5: Profit | B5: =(SUMIFS(Inventory!$S$2:$S$501,Inventory!$L$2:$L$501,"Sold")+SUMIFS(Inventory!$S$2:$S$501,Inventory!$L$2:$L$501,"Shipped")) -> 30.49
A6: Items sold | B6: =(COUNTIFS(Inventory!$L$2:$L$501,"Sold")+COUNTIFS(Inventory!$L$2:$L$501,"Shipped")) -> 1
A7: Avg profit per sale | B7: =IFERROR(B5/B6,0) -> 30.49
A8: Avg days to sell | B8: =IFERROR((SUMIFS(Inventory!$T$2:$T$501,Inventory!$L$2:$L$501,"Sold")+SUMIFS(Inventory!$T$2:$T$501,Inventory!$L$2:$L$501,"Shipped"))/(COUNTIFS(Inventory!$L$2:$L$501,"Sold")+COUNTIFS(Inventory!$L$2:$L$501,"Shipped")),0) -> 6
A9: Listed (unsold) | B9: =COUNTIFS(Inventory!$L$2:$L$501,"Listed") -> 0
A10: Unlisted | B10: =COUNTIFS(Inventory!$L$2:$L$501,"Unlisted") -> 0
A11: Stale listings | B11: =COUNTIFS(Inventory!$V$2:$V$501,"STALE") -> 0
A12: Money tied up in unsold stock | B12: =SUMIFS(Inventory!$I$2:$I$501,Inventory!$L$2:$L$501,"Listed")+SUMIFS(Inventory!$I$2:$I$501,Inventory!$L$2:$L$501,"Unlisted") -> 0
A15: By Platform
A16: Platform | B16: Sold | C16: Revenue | D16: Profit | E16: Avg profit
A17: Depop | B17: =(COUNTIFS(Inventory!$L$2:$L$501,"Sold",Inventory!$K$2:$K$501,$A17)+COUNTIFS(Inventory!$L$2:$L$501,"Shipped",Inventory!$K$2:$K$501,$A17)) -> 1 | C17: =(SUMIFS(Inventory!$Q$2:$Q$501,Inventory!$L$2:$L$501,"Sold",Inventory!$K$2:$K$501,$A17)+SUMIFS(Inventory!$Q$2:$Q$501,Inventory!$L$2:$L$501,"Shipped",Inventory!$K$2:$K$501,$A17)) -> 32 | D17: =(SUMIFS(Inventory!$S$2:$S$501,Inventory!$L$2:$L$501,"Sold",Inventory!$K$2:$K$501,$A17)+SUMIFS(Inventory!$S$2:$S$501,Inventory!$L$2:$L$501,"Shipped",Inventory!$K$2:$K$501,$A17)) -> 30.49 | E17: =IFERROR(D17/B17,0) -> 30.49
A18: Vinted | B18: =(COUNTIFS(Inventory!$L$2:$L$501,"Sold",Inventory!$K$2:$K$501,$A18)+COUNTIFS(Inventory!$L$2:$L$501,"Shipped",Inventory!$K$2:$K$501,$A18)) -> 0 | C18: =(SUMIFS(Inventory!$Q$2:$Q$501,Inventory!$L$2:$L$501,"Sold",Inventory!$K$2:$K$501,$A18)+SUMIFS(Inventory!$Q$2:$Q$501,Inventory!$L$2:$L$501,"Shipped",Inventory!$K$2:$K$501,$A18)) -> 0 | D18: =(SUMIFS(Inventory!$S$2:$S$501,Inventory!$L$2:$L$501,"Sold",Inventory!$K$2:$K$501,$A18)+SUMIFS(Inventory!$S$2:$S$501,Inventory!$L$2:$L$501,"Shipped",Inventory!$K$2:$K$501,$A18)) -> 0 | E18: =IFERROR(D18/B18,0) -> 0
A19: Other | B19: =(COUNTIFS(Inventory!$L$2:$L$501,"Sold",Inventory!$K$2:$K$501,$A19)+COUNTIFS(Inventory!$L$2:$L$501,"Shipped",Inventory!$K$2:$K$501,$A19)) -> 0 | C19: =(SUMIFS(Inventory!$Q$2:$Q$501,Inventory!$L$2:$L$501,"Sold",Inventory!$K$2:$K$501,$A19)+SUMIFS(Inventory!$Q$2:$Q$501,Inventory!$L$2:$L$501,"Shipped",Inventory!$K$2:$K$501,$A19)) -> 0 | D19: =(SUMIFS(Inventory!$S$2:$S$501,Inventory!$L$2:$L$501,"Sold",Inventory!$K$2:$K$501,$A19)+SUMIFS(Inventory!$S$2:$S$501,Inventory!$L$2:$L$501,"Shipped",Inventory!$K$2:$K$501,$A19)) -> 0 | E19: =IFERROR(D19/B19,0) -> 0
A22: By Source
A23: Source | B23: Sold | C23: Revenue | D23: Profit | E23: Avg profit
A24: In Person | B24: =(COUNTIFS(Inventory!$L$2:$L$501,"Sold",Inventory!$H$2:$H$501,$A24)+COUNTIFS(Inventory!$L$2:$L$501,"Shipped",Inventory!$H$2:$H$501,$A24)) -> 0 | C24: =(SUMIFS(Inventory!$Q$2:$Q$501,Inventory!$L$2:$L$501,"Sold",Inventory!$H$2:$H$501,$A24)+SUMIFS(Inventory!$Q$2:$Q$501,Inventory!$L$2:$L$501,"Shipped",Inventory!$H$2:$H$501,$A24)) -> 0 | D24: =(SUMIFS(Inventory!$S$2:$S$501,Inventory!$L$2:$L$501,"Sold",Inventory!$H$2:$H$501,$A24)+SUMIFS(Inventory!$S$2:$S$501,Inventory!$L$2:$L$501,"Shipped",Inventory!$H$2:$H$501,$A24)) -> 0 | E24: =IFERROR(D24/B24,0) -> 0
A25: Wholesale | B25: =(COUNTIFS(Inventory!$L$2:$L$501,"Sold",Inventory!$H$2:$H$501,$A25)+COUNTIFS(Inventory!$L$2:$L$501,"Shipped",Inventory!$H$2:$H$501,$A25)) -> 0 | C25: =(SUMIFS(Inventory!$Q$2:$Q$501,Inventory!$L$2:$L$501,"Sold",Inventory!$H$2:$H$501,$A25)+SUMIFS(Inventory!$Q$2:$Q$501,Inventory!$L$2:$L$501,"Shipped",Inventory!$H$2:$H$501,$A25)) -> 0 | D25: =(SUMIFS(Inventory!$S$2:$S$501,Inventory!$L$2:$L$501,"Sold",Inventory!$H$2:$H$501,$A25)+SUMIFS(Inventory!$S$2:$S$501,Inventory!$L$2:$L$501,"Shipped",Inventory!$H$2:$H$501,$A25)) -> 0 | E25: =IFERROR(D25/B25,0) -> 0
A26: Whatnot | B26: =(COUNTIFS(Inventory!$L$2:$L$501,"Sold",Inventory!$H$2:$H$501,$A26)+COUNTIFS(Inventory!$L$2:$L$501,"Shipped",Inventory!$H$2:$H$501,$A26)) -> 0 | C26: =(SUMIFS(Inventory!$Q$2:$Q$501,Inventory!$L$2:$L$501,"Sold",Inventory!$H$2:$H$501,$A26)+SUMIFS(Inventory!$Q$2:$Q$501,Inventory!$L$2:$L$501,"Shipped",Inventory!$H$2:$H$501,$A26)) -> 0 | D26: =(SUMIFS(Inventory!$S$2:$S$501,Inventory!$L$2:$L$501,"Sold",Inventory!$H$2:$H$501,$A26)+SUMIFS(Inventory!$S$2:$S$501,Inventory!$L$2:$L$501,"Shipped",Inventory!$H$2:$H$501,$A26)) -> 0 | E26: =IFERROR(D26/B26,0) -> 0
A27: Free | B27: =(COUNTIFS(Inventory!$L$2:$L$501,"Sold",Inventory!$H$2:$H$501,$A27)+COUNTIFS(Inventory!$L$2:$L$501,"Shipped",Inventory!$H$2:$H$501,$A27)) -> 1 | C27: =(SUMIFS(Inventory!$Q$2:$Q$501,Inventory!$L$2:$L$501,"Sold",Inventory!$H$2:$H$501,$A27)+SUMIFS(Inventory!$Q$2:$Q$501,Inventory!$L$2:$L$501,"Shipped",Inventory!$H$2:$H$501,$A27)) -> 32 | D27: =(SUMIFS(Inventory!$S$2:$S$501,Inventory!$L$2:$L$501,"Sold",Inventory!$H$2:$H$501,$A27)+SUMIFS(Inventory!$S$2:$S$501,Inventory!$L$2:$L$501,"Shipped",Inventory!$H$2:$H$501,$A27)) -> 30.49 | E27: =IFERROR(D27/B27,0) -> 30.49
A28: Other | B28: =(COUNTIFS(Inventory!$L$2:$L$501,"Sold",Inventory!$H$2:$H$501,$A28)+COUNTIFS(Inventory!$L$2:$L$501,"Shipped",Inventory!$H$2:$H$501,$A28)) -> 0 | C28: =(SUMIFS(Inventory!$Q$2:$Q$501,Inventory!$L$2:$L$501,"Sold",Inventory!$H$2:$H$501,$A28)+SUMIFS(Inventory!$Q$2:$Q$501,Inventory!$L$2:$L$501,"Shipped",Inventory!$H$2:$H$501,$A28)) -> 0 | D28: =(SUMIFS(Inventory!$S$2:$S$501,Inventory!$L$2:$L$501,"Sold",Inventory!$H$2:$H$501,$A28)+SUMIFS(Inventory!$S$2:$S$501,Inventory!$L$2:$L$501,"Shipped",Inventory!$H$2:$H$501,$A28)) -> 0 | E28: =IFERROR(D28/B28,0) -> 0

Sheet How To Use
A1: Reselling Tracker — Depop + Vinted
A3: Workflow
A4: 1. Add a row in Inventory the day you get a piece (even if it was free). Give it an ID and write that ID on its tag/bin.
A5: 2. When you list it: set Platform, Status = Listed, Date Listed, List Price.
A6: 3. When it sells: Status = Sold, fill Date Sold and Sold Price. Fees and Profit calculate automatically.
A7: 4. After you ship it: Status = Shipped.
A9: Which cells to edit
A10: Yellow cells / blue text = you type here. Grey/black cells = formulas, don't type over them.
A11: Inventory: columns A–Q and U are yours. R (Fees), S (Profit), T (Days), V (Flag) are automatic.
A12: Settings: fee rates per platform — check them against a real sale and update if they're off.
A14: Flags
A15: STALE = listed 30+ days without selling (change the number on Settings). Consider a price drop, bundle, or relist.
... A20: Row 2 of Inventory is an example — overwrite or delete it.

Sheet Inventory
A1: ID | B1: Item | C1: Brand | D1: Category | E1: Era | F1: Size | G1: Condition | H1: Source | I1: Cost | J1: Bin / Location | K1: Platform | L1: Status | M1: Date Bought | N1: Date Listed | O1: List Price | P1: Date Sold | Q1: Sold Price | R1: Fees | S1: Profit | T1: Days Listed / To Sell | U1: Notes | V1: Flag
A2: V-0001 | B2: Example: Y2K baby tee | C2: Baby Phat | D2: Top | E2: Y2K (2000s) | F2: M | G2: Good | H2: Free | I2: 0 | J2: Bin A | K2: Depop | L2: Sold | M2: 46314 | N2: 46315 | O2: 35 | P2: 46321 | Q2: 32 | R2: =IF(Q2="","",ROUND(Q2*IFERROR(INDEX(Settings!$B$2:$B$4,MATCH(K2,Settings!$A$2:$A$4,0)),0)+IFERROR(INDEX(Settings!$C$2:$C$4,MATCH(K2,Settings!$A$2:$A$4,0)),0),2)) -> 1.51 | S2: =IF(Q2="","",Q2-R2-N(I2)) -> 30.49 | T2: =IF(N2="","",IF(P2<>"",P2-N2,TODAY()-N2)) -> 6 | U2: Example row — delete me | V2: =IF(AND(L2="Listed",N2<>"",P2=""),IF(TODAY()-N2>=Settings!$B$6,"STALE",""),"")
R3: =IF(Q3="","",ROUND(Q3*IFERROR(INDEX(Settings!$B$2:$B$4,MATCH(K3,Settings!$A$2:$A$4,0)),0)+IFERROR(INDEX(Settings!$C$2:$C$4,MATCH(K3,Settings!$A$2:$A$4,0)),0),2)) | S3: =IF(Q3="","",Q3-R3-N(I3)) | T3: =IF(N3="","",IF(P3<>"",P3-N3,TODAY()-N3)) | V3: =IF(AND(L3="Listed",N3<>"",P3=""),IF(TODAY()-N3>=Settings!$B$6,"STALE",""),"")
R4: =IF(Q4="","",ROUND(Q4*IFERROR(INDEX(Settings!$B$2:$B$4,MATCH(K4,Settings!$A$2:$A$4,0)),0)+IFERROR(INDEX(Settings!$C$2:$C$4,MATCH(K4,Settings!$A$2:$A$4,0)),0),2)) | S4: =IF(Q4="","",Q4-R4-N(I4)) | T4: =IF(N4="","",IF(P4<>"",P4-N4,TODAY()-N4)) | V4: =IF(AND(L4="Listed",N4<>"",P4=""),IF(TODAY()-N4>=Settings!$B$6,"STALE",""),"")
R5: =IF(Q5="","",ROUND(Q5*IFERROR(INDEX(Settings!$B$2:$B$4,MATCH(K5,Settings!$A$2:$A$4,0)),0)+IFERROR(INDEX(Settings!$C$2:$C$4,MATCH(K5,Settings!$A$2:$A$4,0)),0),2)) | S5: =IF(Q5="","",Q5-R5-N(I5)) | T5: =IF(N5="","",IF(P5<>"",P5-N5,TODAY()-N5)) | V5: =IF(AND(L5="Listed",N5<>"",P5=""),IF(TODAY()-N5>=Settings!$B$6,"STALE",""),"")
R6: =IF(Q6="","",ROUND(Q6*IFERROR(INDEX(Settings!$B$2:$B$4,MATCH(K6,Settings!$A$2:$A$4,0)),0)+IFERROR(INDEX(Settings!$C$2:$C$4,MATCH(K6,Settings!$A$2:$A$4,0)),0),2)) | S6: =IF(Q6="","",Q6-R6-N(I6)) | T6: =IF(N6="","",IF(P6<>"",P6-N6,TODAY()-N6)) | V6: =IF(AND(L6="Listed",N6<>"",P6=""),IF(TODAY()-N6>=Settings!$B$6,"STALE",""),"")
R7: =IF(Q7="","",ROUND(Q7*IFERROR(INDEX(Settings!$B$2:$B$4,MATCH(K7,Settings!$A$2:$A$4,0)),0)+IFERROR(INDEX(Settings!$C$2:$C$4,MATCH(K7,Settings!$A$2:$A$4,0)),0),2)) | S7: =IF(Q7="","",Q7-R7-N(I7)) | T7: =IF(N7="","",IF(P7<>"",P7-N7,TODAY()-N7)) | V7: =IF(AND(L7="Listed",N7<>"",P7=""),IF(TODAY()-N7>=Settings!$B$6,"STALE",""),"")
R8: =IF(Q8="","",ROUND(Q8*IFERROR(INDEX(Settings!$B$2:$B$4,MATCH(K8,Settings!$A$2:$A$4,0)),0)+IFERROR(INDEX(Settings!$C$2:$C$4,MATCH(K8,Settings!$A$2:$A$4,0)),0),2)) | S8: =IF(Q8="","",Q8-R8-N(I8)) | T8: =IF(N8="","",IF(P8<>"",P8-N8,TODAY()-N8)) | V8: =IF(AND(L8="Listed",N8<>"",P8=""),IF(TODAY()-N8>=Settings!$B$6,"STALE",""),"")
R9: =IF(Q9="","",ROUND(Q9*IFERROR(INDEX(Settings!$B$2:$B$4,MATCH(K9,Settings!$A$2:$A$4,0)),0)+IFERROR(INDEX(Settings!$C$2:$C$4,MATCH(K9,Settings!$A$2:$A$4,0)),0),2)) | S9: =IF(Q9="","",Q9-R9-N(I9)) | T9: =IF(N9="","",IF(P9<>"",P9-N9,TODAY()-N9)) | V9: =IF(AND(L9="Listed",N9<>"",P9=""),IF(TODAY()-N9>=Settings!$B$6,"STALE",""),"")
R10: =IF(Q10="","",ROUND(Q10*IFERROR(INDEX(Settings!$B$2:$B$4,MATCH(K10,Settings!$A$2:$A$4,0)),0)+IFERROR(INDEX(Settings!$C$2:$C$4,MATCH(K10,Settings!$A$2:$A$4,0)),0),2)) | S10: =IF(Q10="","",Q10-R10-N(I10)) | T10: =IF(N10="","",IF(P10<>"",P10-N10,TODAY()-N10)) | V10: =IF(AND(L10="Listed",N10<>"",P10=""),IF(TODAY()-N10>=Settings!$B$6,"STALE",""),"")
R11: =IF(Q11="","",ROUND(Q11*IFERROR(INDEX(Settings!$B$2:$B$4,MATCH(K11,Settings!$A$2:$A$4,0)),0)+IFERROR(INDEX(Settings!$C$2:$C$4,MATCH(K11,Settings!$A$2:$A$4,0)),0),2)) | S11: =IF(Q11="","",Q11-R11-N(I11)) | T11: =IF(N11="","",IF(P11<>"",P11-N11,TODAY()-N11)) | V11: =IF(AND(L11="Listed",N11<>"",P11=""),IF(TODAY()-N11>=Settings!$B$6,"STALE",""),"")
R12: =IF(Q12="","",ROUND(Q12*IFERROR(INDEX(Settings!$B$2:$B$4,MATCH(K12,Settings!$A$2:$A$4,0)),0)+IFERROR(INDEX(Settings!$C$2:$C$4,MATCH(K12,Settings!$A$2:$A$4,0)),0),2)) | S12: =IF(Q12="","",Q12-R12-N(I12)) | T12: =IF(N12="","",IF(P12<>"",P12-N12,TODAY()-N12)) | V12: =IF(AND(L12="Listed",N12<>"",P12=""),IF(TODAY()-N12>=Settings!$B$6,"STALE",""),"")
R13: =IF(Q13="","",ROUND(Q13*IFERROR(INDEX(Settings!$B$2:$B$4,MATCH(K13,Settings!$A$2:$A$4,0)),0)+IFERROR(INDEX(Settings!$C$2:$C$4,MATCH(K13,Settings!$A$2:$A$4,0)),0),2)) | S13: =IF(Q13="","",Q13-R13-N(I13)) | T13: =IF(N13="","",IF(P13<>"",P13-N13,TODAY()-N13)) | V13: =IF(AND(L13="Listed",N13<>"",P13=""),IF(TODAY()-N13>=Settings!$B$6,"STALE",""),"")
R14: =IF(Q14="","",ROUND(Q14*IFERROR(INDEX(Settings!$B$2:$B$4,MATCH(K14,Settings!$A$2:$A$4,0)),0)+IFERROR(INDEX(Settings!$C$2:$C$4,MATCH(K14,Settings!$A$2:$A$4,0)),0),2)) | S14: =IF(Q14="","",Q14-R14-N(I14)) | T14: =IF(N14="","",IF(P14<>"",P14-N14,TODAY()-N14)) | V14: =IF(AND(L14="Listed",N14<>"",P14=""),IF(TODAY()-N14>=Settings!$B$6,"STALE",""),"")
... R501: =IF(Q501="","",ROUND(Q501*IFERROR(INDEX(Settings!$B$2:$B$4,MATCH(K501,Settings!$A$2:$A$4,0)),0)+IFERROR(INDEX(Settings!$C$2:$C$4,MATCH(K501,Settings!$A$2:$A$4,0)),0),2)) | S501: =IF(Q501="","",Q501-R501-N(I501)) | T501: =IF(N501="","",IF(P501<>"",P501-N501,TODAY()-N501)) | V501: =IF(AND(L501="Listed",N501<>"",P501=""),IF(TODAY()-N501>=Settings!$B$6,"STALE",""),"")

Sheet Settings
A1: Platform | B1: Fee % | C1: Flat fee per sale | D1: Notes
A2: Depop | B2: 0.033 | C2: 0.45 | D2: Payment processing fee (approx, US). Verify against one of your sales.
A3: Vinted | B3: 0 | C3: 0 | D3: Buyer usually pays Vinted's fees; seller fee normally $0. Verify.
A4: Other | B4: 0 | C4: 0 | D4: Edit for any other platform.
A6: Stale after (days) | B6: 30
A8: Dropdown lists
A9: Source | B9: Status | C9: Era | D9: Condition
A10: In Person | B10: Unlisted | C10: Pre-1990 | D10: New w/ tags
A11: Wholesale | B11: Listed | C11: 90s | D11: Like new
A12: Whatnot | B12: Sold | C12: Y2K (2000s) | D12: Good
A13: Free | B13: Shipped | C13: 2010s+ | D13: Fair
A14: Other | C14: Modern | D14: Flawed
